crimp/__init__.py
crimp/__main__.py
crimp/runtime.py
crimp/tests/__init__.py
crimp/tests/test_runtime.py
crimp-1.0.1.dist-info/METADATA
crimp-1.0.1.dist-info/RECORD
crimp-1.0.1.dist-info/WHEEL
crimp-1.0.1.dist-info/entry_points.txt
crimp-1.0.1.dist-info/top_level.txt
