Metadata-Version: 2.1
Name: crimp
Version: 1.0.1
Summary: JavaScript (ES5) minifier
Home-page: https://github.com/calmjs/crimp
Author: Tommy Yu
Author-email: tommy.yu@auckland.ac.nz
License: mit
Platform: UNKNOWN
Classifier: Development Status :: 5 - Production/Stable
Classifier: Environment :: Console
Classifier: Intended Audience :: Developers
Classifier: License :: OSI Approved :: MIT License
Classifier: Operating System :: OS Independent
Classifier: Programming Language :: JavaScript
Classifier: Programming Language :: Python :: 2.7
Classifier: Programming Language :: Python :: 3.3
Classifier: Programming Language :: Python :: 3.4
Classifier: Programming Language :: Python :: 3.5
Classifier: Programming Language :: Python :: 3.6
Requires-Dist: calmjs.parse (>=1.1.1)
